pycipapi/__init__.py
pycipapi/cipapi_client.py
pycipapi/models.py
pycipapi/rest_client.py
pycipapi-0.9.4.dist-info/LICENSE
pycipapi-0.9.4.dist-info/METADATA
pycipapi-0.9.4.dist-info/WHEEL
pycipapi-0.9.4.dist-info/top_level.txt
pycipapi-0.9.4.dist-info/RECORD
